mlflow_cratedb/__init__.py
mlflow_cratedb/boot.py
mlflow_cratedb/cli.py
mlflow_cratedb/server.py
mlflow_cratedb/adapter/__init__.py
mlflow_cratedb/adapter/setup_db.py
mlflow_cratedb/adapter/ddl/cratedb.sql
mlflow_cratedb/adapter/ddl/drop.sql
mlflow_cratedb/patch/__init__.py
mlflow_cratedb/patch/sqlalchemy.py
mlflow_cratedb/patch/mlflow/__init__.py
mlflow_cratedb/patch/mlflow/db_types.py
mlflow_cratedb/patch/mlflow/db_utils.py
mlflow_cratedb/patch/mlflow/model.py
mlflow_cratedb/patch/mlflow/search_utils.py
mlflow_cratedb/patch/mlflow/server.py
mlflow_cratedb/patch/mlflow/settings.py
mlflow_cratedb/patch/mlflow/tracking.py
mlflow_cratedb-2.14.1.dist-info/LICENSE
mlflow_cratedb-2.14.1.dist-info/METADATA
mlflow_cratedb-2.14.1.dist-info/WHEEL
mlflow_cratedb-2.14.1.dist-info/entry_points.txt
mlflow_cratedb-2.14.1.dist-info/top_level.txt
mlflow_cratedb-2.14.1.dist-info/RECORD
