Metadata-Version: 2.1
Name: mlflow-cratedb
Version: 2.14.1
Summary: MLflow adapter for CrateDB
Author-email: Andreas Motl <andreas.motl@crate.io>
License: Apache License 2.0
Project-URL: changelog, https://github.com/crate/mlflow-cratedb/blob/main/CHANGES.md
Project-URL: documentation, https://github.com/crate/mlflow-cratedb
Project-URL: homepage, https://github.com/crate/mlflow-cratedb
Project-URL: repository, https://github.com/crate/mlflow-cratedb
Keywords: ai,cratedb,databricks,machine learning,ml,ml-ops,mlflow,mlflow-tracking,mlops
Classifier: Development Status :: 4 - Beta
Classifier: Environment :: Console
Classifier: Intended Audience :: Developers
Classifier: Intended Audience :: Education
Classifier: Intended Audience :: Information Technology
Classifier: Intended Audience :: Telecommunications Industry
Classifier: License :: OSI Approved :: Apache Software License
Classifier: Operating System :: MacOS :: MacOS X
Classifier: Operating System :: POSIX :: Linux
Classifier: Operating System :: Unix
Classifier: Programming Language :: Python
Classifier: Programming Language :: Python :: 3 :: Only
Classifier: Programming Language :: Python :: 3.8
Classifier: Programming Language :: Python :: 3.9
Classifier: Programming Language :: Python :: 3.10
Classifier: Programming Language :: Python :: 3.11
Classifier: Topic :: Communications
Classifier: Topic :: Database
Classifier: Topic :: Database :: Database Engines/Servers
Classifier: Topic :: Database :: Front-Ends
Classifier: Topic :: Education
Classifier: Topic :: Scientific/Engineering
Classifier: Topic :: Scientific/Engineering :: Artificial Intelligence
Classifier: Topic :: Scientific/Engineering :: Information Analysis
Classifier: Topic :: Scientific/Engineering :: Interface Engine/Protocol Translator
Classifier: Topic :: Software Development :: Libraries
Classifier: Topic :: Software Development :: Quality Assurance
Classifier: Topic :: Software Development :: Version Control
Classifier: Topic :: System :: Archiving
Classifier: Topic :: System :: Clustering
Classifier: Topic :: System :: Distributed Computing
Classifier: Topic :: Text Processing
Classifier: Topic :: Utilities
Requires-Python: <3.12,>=3.8
License-File: LICENSE
Requires-Dist: crash
Requires-Dist: dask >=2024.4.1
Requires-Dist: joblib !=1.4.0,<1.5
Requires-Dist: mlflow ==2.14.1
Requires-Dist: sqlalchemy-cratedb <1,>=0.38.0
Requires-Dist: sqlparse <0.6
Provides-Extra: develop
Requires-Dist: black <25 ; extra == 'develop'
Requires-Dist: mypy <1.11 ; extra == 'develop'
Requires-Dist: poethepoet <1 ; extra == 'develop'
Requires-Dist: pyproject-fmt <2.2 ; extra == 'develop'
Requires-Dist: ruff <0.5 ; extra == 'develop'
Requires-Dist: validate-pyproject <0.19 ; extra == 'develop'
Provides-Extra: examples
Requires-Dist: salesforce-merlion <2.1 ; extra == 'examples'
Requires-Dist: werkzeug ==2.2.3 ; extra == 'examples'
Requires-Dist: pycaret[analysis,models,parallel,test,tuner] ==3.3.2 ; (platform_machine != "aarch64") and extra == 'examples'
Provides-Extra: release
Requires-Dist: build <2 ; extra == 'release'
Requires-Dist: twine <6 ; extra == 'release'
Provides-Extra: test
Requires-Dist: psutil ==5.9.8 ; extra == 'test'
Requires-Dist: pytest <9 ; extra == 'test'
Requires-Dist: pytest-cov <6 ; extra == 'test'
